oaklib/__init__.py
oaklib/cli.py
oaklib/conf/__init__.py
oaklib/conf/go-human-input-spec.yaml
oaklib/conf/go-pombase-input-spec.yaml
oaklib/conf/hpoa-g2p-input-spec.yaml
oaklib/conf/hpoa-input-spec.yaml
oaklib/conf/lexmatch-rules-oboinowl-default.yaml
oaklib/conf/mondo-g2d-input-spec.yaml
oaklib/conf/mondo-gencc-input-spec.yaml
oaklib/conf/mondo-hpoa-g2d-input-spec.yaml
oaklib/conf/mondo-medgen-g2d-input-spec.yaml
oaklib/conf/obograph-style.json
oaklib/conf/omo-to-skos.sssom.tsv
oaklib/conf/value-set-expander.conf.yaml
oaklib/constants.py
oaklib/converters/__init__.py
oaklib/converters/data_model_converter.py
oaklib/converters/logical_definition_flattener.py
oaklib/converters/obo_graph_to_cx_converter.py
oaklib/converters/obo_graph_to_fhir_converter.py
oaklib/converters/obo_graph_to_obo_format_converter.py
oaklib/converters/obo_graph_to_rdf_owl_converter.py
oaklib/datamodels/__init__.py
oaklib/datamodels/association.owl.ttl
oaklib/datamodels/association.py
oaklib/datamodels/association.yaml
oaklib/datamodels/class_enrichment.owl.ttl
oaklib/datamodels/class_enrichment.py
oaklib/datamodels/class_enrichment.yaml
oaklib/datamodels/cross_ontology_diff.owl.ttl
oaklib/datamodels/cross_ontology_diff.py
oaklib/datamodels/cross_ontology_diff.yaml
oaklib/datamodels/cx.py
oaklib/datamodels/cx.yaml
oaklib/datamodels/fhir.owl.ttl
oaklib/datamodels/fhir.py
oaklib/datamodels/fhir.yaml
oaklib/datamodels/input_specification.py
oaklib/datamodels/input_specification.yaml
oaklib/datamodels/item_list.py
oaklib/datamodels/item_list.yaml
oaklib/datamodels/lexical_index.owl.ttl
oaklib/datamodels/lexical_index.py
oaklib/datamodels/lexical_index.schema.json
oaklib/datamodels/lexical_index.yaml
oaklib/datamodels/mapping_cluster_datamodel.py
oaklib/datamodels/mapping_cluster_datamodel.yaml
oaklib/datamodels/mapping_rules_datamodel.owl.ttl
oaklib/datamodels/mapping_rules_datamodel.py
oaklib/datamodels/mapping_rules_datamodel.schema.json
oaklib/datamodels/mapping_rules_datamodel.yaml
oaklib-0.6.23.dist-info/LICENSE
oaklib-0.6.23.dist-info/METADATA
oaklib-0.6.23.dist-info/WHEEL
oaklib-0.6.23.dist-info/entry_points.txt
oaklib-0.6.23.dist-info/RECORD
