Metadata-Version: 2.3
Name: oaklib
Version: 0.6.23
Summary: Ontology Access Kit: Python library for common ontology operations over a variety of backends
Author: cmungall
Author-email: cjm@berkeleybop.org
Requires-Python: >=3.9,<4.0.0
Classifier: Programming Language :: Python :: 3
Classifier: Programming Language :: Python :: 3.9
Classifier: Programming Language :: Python :: 3.10
Classifier: Programming Language :: Python :: 3.11
Classifier: Programming Language :: Python :: 3.12
Classifier: Programming Language :: Python :: 3.13
Provides-Extra: bioservices
Provides-Extra: docs
Provides-Extra: gilda
Provides-Extra: llm
Provides-Extra: seaborn
Provides-Extra: semsimian
Requires-Dist: SPARQLWrapper
Requires-Dist: SQLAlchemy (>=1.4.32)
Requires-Dist: aiohttp ; extra == "llm"
Requires-Dist: airium (>=0.2.5)
Requires-Dist: appdirs (>=1.4.4)
Requires-Dist: bioservices ; extra == "bioservices"
Requires-Dist: class-resolver (>=0.4.2)
Requires-Dist: click
Requires-Dist: curies (>=0.6.6)
Requires-Dist: defusedxml (>=0.7.1)
Requires-Dist: eutils (>=0.6.0)
Requires-Dist: funowl (>=0.2.0)
Requires-Dist: gilda (>=1.0.0) ; extra == "gilda"
Requires-Dist: html2text ; extra == "llm"
Requires-Dist: jsonlines
Requires-Dist: kgcl-rdflib (==0.5.0)
Requires-Dist: kgcl-schema (>=0.6.9,<0.7.0)
Requires-Dist: linkml-renderer (>=0.3.0)
Requires-Dist: linkml-runtime (>=1.5.3)
Requires-Dist: llm (>=0.14,<0.15) ; extra == "llm"
Requires-Dist: ndex2 (>=3.5.0)
Requires-Dist: networkx (>=2.7.1)
Requires-Dist: ols-client (>=0.1.1)
Requires-Dist: ontoportal-client (>=0.0.3)
Requires-Dist: prefixmaps (>=0.1.2)
Requires-Dist: pronto (>=2.5.0)
Requires-Dist: pydantic
Requires-Dist: pysolr (>=3.9.0,<4.0.0)
Requires-Dist: pystow (>=0.5.0)
Requires-Dist: ratelimit (>=2.2.1)
Requires-Dist: requests-cache (>=1.0.1,<2.0.0)
Requires-Dist: semsimian (>=0.2.18) ; extra == "semsimian"
Requires-Dist: semsql (>=0.3.1)
Requires-Dist: sssom (>=0.4.4,<0.5.0)
Requires-Dist: tenacity (>=8.2.3)
Requires-Dist: urllib3 (<2) ; extra == "gilda"
